gsay/__init__.py
gsay/cli.py
gsay/gsay.py
gsay-0.1.8.dist-info/METADATA
gsay-0.1.8.dist-info/WHEEL
gsay-0.1.8.dist-info/entry_points.txt
gsay-0.1.8.dist-info/RECORD
